doggopyr/__init__.py
doggopyr/py.typed
doggopyr/tools/__init__.py
doggopyr/tools/helper_functions.py
doggopyr/tools/helper_functions.pyi
doggopyr-0.3.2.dist-info/licenses/LICENSE
doggopyr-0.3.2.dist-info/METADATA
doggopyr-0.3.2.dist-info/WHEEL
doggopyr-0.3.2.dist-info/top_level.txt
doggopyr-0.3.2.dist-info/RECORD
