Metadata-Version: 2.4
Name: doggopyr
Version: 0.3.2
Summary: Dedicated to my Pyrenees mountain doggo. A collection of helper functions for common data operations.
Author: Ken Cat
Classifier: Programming Language :: Python :: 3
Classifier: License :: OSI Approved :: MIT License
Classifier: Operating System :: OS Independent
Classifier: Development Status :: 3 - Alpha
Classifier: Intended Audience :: Developers
Classifier: Topic :: Database
Classifier: Topic :: Software Development :: Libraries :: Python Modules
Requires-Python: >=3.8
License-File: LICENSE
Requires-Dist: pandas
Requires-Dist: python-dotenv
Requires-Dist: SQLAlchemy
Requires-Dist: psycopg2-binary
Requires-Dist: sqlglot
Requires-Dist: pyspark
Dynamic: license-file
